delphai_rpc/__init__.py
delphai_rpc/client.py
delphai_rpc/errors.py
delphai_rpc/metrics.py
delphai_rpc/models.py
delphai_rpc/queue_client.py
delphai_rpc/server.py
delphai_rpc/utils.py
delphai_rpc/workflow.py
delphai_rpc-5.3.4.dist-info/METADATA
delphai_rpc-5.3.4.dist-info/WHEEL
delphai_rpc-5.3.4.dist-info/RECORD
