Metadata-Version: 2.4
Name: delphai-rpc
Version: 5.3.4
Summary: Queue-based RPC client, server and workflow
Author: Anton Ryzhov
Author-email: anton@delphai.com
Requires-Python: >=3.11,<4.0
Classifier: Programming Language :: Python :: 3
Classifier: Programming Language :: Python :: 3.11
Classifier: Programming Language :: Python :: 3.12
Classifier: Programming Language :: Python :: 3.13
Classifier: Programming Language :: Python :: 3.14
Requires-Dist: aio-pika (>=9.4,<10.0)
Requires-Dist: msgpack (>=1,<2)
Requires-Dist: prometheus-client (>=0.4,<0.21)
Requires-Dist: pydantic (>=2.6.0,<3.0.0)
Requires-Dist: tenacity (>=8,<9)
Requires-Dist: zstandard (>=0.23.0,<0.24.0)
